tilesman
