Metadata-Version: 1.2
Name: tilesman
Version: 0.2.4
Summary: A library to tile photos at different resolution levels, for loading performance
Home-page: https://gitlab.com/furzedo/tilesman
Author: Fernando Urzedo
Author-email: furzedo@yahoo.com
License: LICENSE.txt
Platform: UNKNOWN
Requires-Python: >=3.3
